[{
        "path": "wszt",
        "bkName": "王者荣耀",
        "bkIcon": "https://img4.nga.178.com/proxy/cache_attach/ficon/516u.png?423",
        "bkDescription": ""
    },
    {
        "path": "wszt",
        "bkName": "大漩涡",
        "bkIcon": "https://img4.nga.178.com/proxy/cache_attach/ficon/-7u.png?776",
        "bkDescription": ""
    },
    {
        "path": "wszt",
        "bkName": "消费电子 IT新闻",
        "bkIcon": "https://img4.nga.178.com/proxy/cache_attach/ficon/436u.png?086",
        "bkDescription": ""
    }
]